hetzner_control/__init__.py
hetzner_control/cli.py
hetzner_control/commands/__init__.py
hetzner_control/commands/datacenters.py
hetzner_control/commands/info.py
hetzner_control/commands/price.py
hetzner_control/commands/server.py
hetzner_control/commands/server_types.py
hetzner_control/core/__init__.py
hetzner_control/core/datacenters.py
hetzner_control/core/exceptions.py
hetzner_control/core/pricing.py
hetzner_control/core/server.py
hetzner_control/core/server_types.py
hetzner_control-1.0.0.dist-info/entry_points.txt
hetzner_control-1.0.0.dist-info/LICENSE
hetzner_control-1.0.0.dist-info/WHEEL
hetzner_control-1.0.0.dist-info/METADATA
hetzner_control-1.0.0.dist-info/RECORD
