Metadata-Version: 2.1
Name: hetzner-control
Version: 1.0.0
Summary: CLI application for managing servers on the Hetzner platform
License: MIT
Author: Hanabira
Author-email: workflow.elec@gmail.com
Requires-Python: >=3.8,<4.0
Classifier: License :: OSI Approved :: MIT License
Classifier: Programming Language :: Python :: 3
Classifier: Programming Language :: Python :: 3.10
Classifier: Programming Language :: Python :: 3.8
Classifier: Programming Language :: Python :: 3.9
Requires-Dist: requests (>=2.27.1,<3.0.0)
Requires-Dist: rich (>=12.0.0,<13.0.0)
Requires-Dist: typer (>=0.4.0,<0.5.0)
